hurdle/__init__.py
hurdle/hurdle.py
hurdle/menu_hurdle_estimator.py
hurdle-2.0.0.dist-info/LICENSE
hurdle-2.0.0.dist-info/WHEEL
hurdle-2.0.0.dist-info/METADATA
hurdle-2.0.0.dist-info/RECORD
