Metadata-Version: 2.1
Name: hurdle
Version: 2.0.0
Summary: Scikit hurdle estimator
Home-page: https://www.github.com/prio-data/hurdle
Author: peder2911
Author-email: pglandsverk@gmail.com
Requires-Python: >=3.8,<4.0
Classifier: Programming Language :: Python :: 3
Classifier: Programming Language :: Python :: 3.10
Classifier: Programming Language :: Python :: 3.8
Classifier: Programming Language :: Python :: 3.9
Requires-Dist: scikit-learn (>=1.0.2,<2.0.0)
